codebugger/__init__.py
codebugger/codebug.py
Codebugger-0.0.1.dist-info/LICENSE
Codebugger-0.0.1.dist-info/METADATA
Codebugger-0.0.1.dist-info/WHEEL
Codebugger-0.0.1.dist-info/top_level.txt
Codebugger-0.0.1.dist-info/RECORD
